setup.py
tomoDDUtility/__init__.py
tomoDDUtility/syn_utility.py
tomoDDUtility/tomodd_utility.py
tomoDDUtility/utility.py
tomoDDUtility/writeTomoDDInp.py
tomoDDUtility.egg-info/PKG-INFO
tomoDDUtility.egg-info/SOURCES.txt
tomoDDUtility.egg-info/dependency_links.txt
tomoDDUtility.egg-info/requires.txt
tomoDDUtility.egg-info/top_level.txt