Metadata-Version: 1.0
Name: tomoDDUtility
Version: 0.0.1
Summary: tomoDDUtility
Home-page: https://github.com/jhsa26
Author: Jing Hu
Author-email: jhsa920@163.com
License: UNKNOWN
Platform: UNKNOWN
